{
  "timestamp": "20260417_224825",
  "data": {
    "source": "LAppLive2DManager.onUpdate.isLeftButtonPressed_debug",
    "timestamp": 1776437077034,
    "dragX": -0.00034588214795451024,
    "dragY": 0.0014469493033028094,
    "isLeftButtonPressed": false,
    "modelMatrixY": 0.5,
    "modelParams": {
      "ParamAngleX": -7.415754795074463,
      "ParamAngleY": -3.8958911895751953,
      "ParamEyeBallX": -0.00034588214475661516,
      "ParamEyeBallY": 0.0014469493180513382,
      "ParamBodyAngleX": -1116.921593414889
    }
  }
}