{
  "timestamp": "20260417_225232",
  "data": {
    "source": "LAppLive2DManager.onUpdate.isLeftButtonPressed_debug",
    "timestamp": 1776437552011,
    "dragX": 0.021347316384303223,
    "dragY": -0.4589465163803348,
    "isLeftButtonPressed": true,
    "modelMatrixY": 0.5,
    "modelParams": {
      "ParamAngleX": -6.512510299682617,
      "ParamAngleY": -10.206914901733398,
      "ParamEyeBallX": 0.02134731598198414,
      "ParamEyeBallY": -0.4589465260505676,
      "ParamBodyAngleX": 162.63574291353774
    }
  }
}