{
  "timestamp": "20260417_222813",
  "data": {
    "source": "LAppLive2DManager.onUpdate.isLeftButtonPressed_debug",
    "timestamp": 1776435865884,
    "dragX": -0.00034588214795451024,
    "dragY": 0.0014469493033028094,
    "isLeftButtonPressed": false,
    "modelMatrixY": 0.5,
    "modelParams": {
      "ParamAngleX": 5.207797527313232,
      "ParamAngleY": 2.6377859115600586,
      "ParamEyeBallX": -0.00034588214475661516,
      "ParamEyeBallY": 0.0014469493180513382,
      "ParamBodyAngleX": -835.0308542983531
    }
  }
}