{
  "timestamp": "20260417_234658",
  "data": {
    "source": "LAppLive2DManager.onUpdate.isLeftButtonPressed_debug",
    "timestamp": 1776440802488,
    "dragX": 0.001320072727364576,
    "dragY": -1.2290140084738579,
    "isLeftButtonPressed": true,
    "modelMatrixY": 0.5,
    "modelParams": {
      "ParamAngleX": 5.6359710693359375,
      "ParamAngleY": -27.07191276550293,
      "ParamEyeBallX": 0.0013200726825743914,
      "ParamEyeBallY": -1,
      "ParamBodyAngleX": -92.32585408592834
    }
  }
}