{
  "timestamp": "20260417_223534",
  "data": {
    "source": "LAppLive2DManager.onUpdate.isLeftButtonPressed_debug",
    "timestamp": 1776436533592,
    "dragX": -0.047009592290461054,
    "dragY": -0.1873414383850197,
    "isLeftButtonPressed": true,
    "modelMatrixY": 0.5,
    "modelParams": {
      "ParamAngleX": -6.9523186683654785,
      "ParamAngleY": -1.729243516921997,
      "ParamEyeBallX": -0.04700959101319313,
      "ParamEyeBallY": -0.18734143674373627,
      "ParamBodyAngleX": -8980.493493280304
    }
  }
}