{
  "timestamp": "20260417_211026",
  "data": {
    "source": "LAppLive2DManager.onUpdate.isLeftButtonPressed_debug",
    "timestamp": 1776431423028,
    "dragX": -0.020627045866797446,
    "dragY": -0.3273921766054185,
    "isLeftButtonPressed": true,
    "modelMatrixY": 0.5,
    "modelParams": {
      "ParamAngleX": 1.3500354290008545,
      "ParamAngleY": -6.131626605987549,
      "ParamEyeBallX": -0.02062704600393772,
      "ParamEyeBallY": -0.32739219069480896,
      "ParamBodyAngleX": -1648.3636634563097
    }
  }
}