{
  "timestamp": "20260417_210945",
  "data": {
    "source": "LAppLive2DManager.onUpdate.isLeftButtonPressed_debug",
    "timestamp": 1776431379640,
    "dragX": 0.0008345942526357159,
    "dragY": -1.003172673264562,
    "isLeftButtonPressed": true,
    "modelMatrixY": 0.5,
    "modelParams": {
      "ParamAngleX": -6.802909851074219,
      "ParamAngleY": -29.06652069091797,
      "ParamEyeBallX": 0.0008345942478626966,
      "ParamEyeBallY": -1,
      "ParamBodyAngleX": -1291.478299471541
    }
  }
}