{
  "timestamp": "20260417_203844",
  "data": {
    "source": "LAppLive2DManager.onUpdate.isLeftButtonPressed_debug",
    "timestamp": 1776429318534,
    "dragX": -0.4753179108153042,
    "dragY": -0.11780310285191758,
    "isLeftButtonPressed": false,
    "modelMatrixY": 0.5,
    "modelParams": {
      "ParamAngleX": -17.745574951171875,
      "ParamAngleY": 0.08382117003202438,
      "ParamEyeBallX": -0.47531792521476746,
      "ParamEyeBallY": -0.11780310422182083,
      "ParamBodyAngleX": 488.2287899839563
    }
  }
}