{
  "timestamp": "20260417_234005",
  "data": {
    "source": "LAppLive2DManager.onUpdate.isLeftButtonPressed_debug",
    "timestamp": 1776440103640,
    "dragX": -0.00034588214795451024,
    "dragY": 0.0014469493033028094,
    "isLeftButtonPressed": false,
    "modelMatrixY": 0.5,
    "modelParams": {
      "ParamAngleX": -4.500332355499268,
      "ParamAngleY": 1.9998900890350342,
      "ParamEyeBallX": -0.00034588214475661516,
      "ParamEyeBallY": 0.0014469493180513382,
      "ParamBodyAngleX": -1657.238557583931
    }
  }
}