{
  "timestamp": "20260417_233701",
  "data": {
    "source": "LAppLive2DManager.onUpdate.isLeftButtonPressed_debug",
    "timestamp": 1776439920197,
    "dragX": -0.00034588214795451024,
    "dragY": 0.0014469493033028094,
    "isLeftButtonPressed": false,
    "modelMatrixY": 0.5,
    "modelParams": {
      "ParamAngleX": -6.699338436126709,
      "ParamAngleY": 3.6666128635406494,
      "ParamEyeBallX": -0.00034588214475661516,
      "ParamEyeBallY": 0.0014469493180513382,
      "ParamBodyAngleX": -1610.6492394782356
    }
  }
}