{
  "timestamp": "20260417_202225",
  "data": {
    "source": "LAppLive2DManager.onUpdate.isLeftButtonPressed_debug",
    "timestamp": 1776428545209,
    "dragX": -0.16199919031058974,
    "dragY": -0.18387302636806238,
    "isLeftButtonPressed": true,
    "modelMatrixY": 0.5,
    "modelParams": {
      "ParamAngleX": -7.259921073913574,
      "ParamAngleY": -1.8854905366897583,
      "ParamEyeBallX": -0.1619991958141327,
      "ParamEyeBallY": -0.1838730275630951,
      "ParamBodyAngleX": -1861.1347954009304
    }
  }
}