{
  "timestamp": "20260417_215629",
  "data": {
    "source": "LAppLive2DManager.onUpdate.isLeftButtonPressed_debug",
    "timestamp": 1776434189222,
    "dragX": 0.07523101766359379,
    "dragY": -0.8830178999889866,
    "isLeftButtonPressed": true,
    "modelMatrixY": 0.5,
    "modelParams": {
      "ParamAngleX": 8.579633712768555,
      "ParamAngleY": -30,
      "ParamEyeBallX": 0.07523101568222046,
      "ParamEyeBallY": -0.883017897605896,
      "ParamBodyAngleX": -14.662711659469963
    }
  }
}