{
  "timestamp": "20260417_222637",
  "data": {
    "source": "LAppLive2DManager.onUpdate.isLeftButtonPressed_debug",
    "timestamp": 1776435771281,
    "dragX": -0.00034588214795451024,
    "dragY": 0.0014469493033028094,
    "isLeftButtonPressed": false,
    "modelMatrixY": 0.5,
    "modelParams": {
      "ParamAngleX": -4.416140079498291,
      "ParamAngleY": 3.3271663188934326,
      "ParamEyeBallX": -0.00034588214475661516,
      "ParamEyeBallY": 0.0014469493180513382,
      "ParamBodyAngleX": -766.0715763949347
    }
  }
}