{
  "timestamp": "20260417_212250",
  "data": {
    "source": "LAppLive2DManager.onUpdate.isLeftButtonPressed_debug",
    "timestamp": 1776432143123,
    "dragX": 0.006574345010864007,
    "dragY": -0.4076368098027249,
    "isLeftButtonPressed": true,
    "modelMatrixY": 0.5,
    "modelParams": {
      "ParamAngleX": 3.4383575916290283,
      "ParamAngleY": -14.915607452392578,
      "ParamEyeBallX": 0.0065743448212742805,
      "ParamEyeBallY": -0.407636821269989,
      "ParamBodyAngleX": -148.6871145159703
    }
  }
}