{
  "timestamp": "20260419_172523",
  "data": {
    "type": "nativeTouchDrag",
    "source": "LAppView.onTouchesMoved",
    "pointX": 183.0357403755188,
    "pointY": 296.67862367630005,
    "touchStartX": 139.96429443359375,
    "touchStartY": 342.4285888671875,
    "deltaX": 43.07144594192505,
    "deltaY": -45.74996519088745,
    "dragX": 0.46065717584946575,
    "dragY": 0.28638475862840346,
    "canvasWidth": 374,
    "canvasHeight": 639,
    "touchManagerX": 640.6250913143158,
    "touchManagerY": 1038.3751828670502,
    "devicePixelRatio": 3.5,
    "_deviceToScreen_tr5": -0.0010416667209938169,
    "_viewMatrix_tr5": 1
  }
}